schema_dataclass/__init__.py
schema_dataclass/dataclass.py
schema_dataclass/exceptions.py
schema_dataclass/fields.py
schema_dataclass-0.0.2.dist-info/METADATA
schema_dataclass-0.0.2.dist-info/WHEEL
schema_dataclass-0.0.2.dist-info/licenses/LICENSE
schema_dataclass-0.0.2.dist-info/RECORD
