Metadata-Version: 2.4
Name: schema-dataclass
Version: 0.0.2
Summary: Python 2/3 兼容的 DataClass 库，支持完整的数据校验功能和自定义错误消息
Project-URL: Homepage, https://github.com/b40yd/schemas-python
Project-URL: Documentation, https://github.com/b40yd/schemas-python/blob/main/README.md
Project-URL: Repository, https://github.com/b40yd/schemas-python.git
Project-URL: Bug Reports, https://github.com/b40yd/schemas-python/issues
Project-URL: Changelog, https://github.com/b40yd/schemas-python/blob/main/CHANGELOG.md
Author-email: Schemas DataClass Team <bb.qnyd@gmail.com>
Maintainer-email: Schemas DataClass Team <bb.qnyd@gmail.com>
License-Expression: GPL-3.0-or-later
License-File: LICENSE
Keywords: dataclass,fields,python2,python3,schema,validation
Classifier: Development Status :: 5 - Production/Stable
Classifier: Intended Audience :: Developers
Classifier: License :: OSI Approved :: GNU General Public License v3 (GPLv3)
Classifier: Operating System :: OS Independent
Classifier: Programming Language :: Python
Classifier: Programming Language :: Python :: 2
Classifier: Programming Language :: Python :: 2.7
Classifier: Programming Language :: Python :: 3
Classifier: Programming Language :: Python :: 3.4
Classifier: Programming Language :: Python :: 3.5
Classifier: Programming Language :: Python :: 3.6
Classifier: Programming Language :: Python :: 3.7
Classifier: Programming Language :: Python :: 3.8
Classifier: Programming Language :: Python :: 3.9
Classifier: Programming Language :: Python :: 3.10
Classifier: Programming Language :: Python :: 3.11
Classifier: Programming Language :: Python :: 3.12
Classifier: Topic :: Software Development :: Libraries :: Python Modules
Classifier: Topic :: Utilities
Requires-Python: >=3.8
Provides-Extra: dev
Requires-Dist: black>=22.0.0; extra == 'dev'
Requires-Dist: flake8>=4.0.0; extra == 'dev'
Requires-Dist: pytest-cov>=3.10.0; extra == 'dev'
Requires-Dist: pytest-mock>=3.0.0; extra == 'dev'
Requires-Dist: pytest-xdist>=2.0.0; extra == 'dev'
Requires-Dist: pytest>=6.0.0; extra == 'dev'
Requires-Dist: tox>=3.20.0; extra == 'dev'
Provides-Extra: docs
Requires-Dist: sphinx-rtd-theme>=1.0.0; extra == 'docs'
Requires-Dist: sphinx>=4.0.0; extra == 'docs'
Provides-Extra: test
Requires-Dist: pytest-cov>=3.10.0; extra == 'test'
Requires-Dist: pytest-mock>=3.14.1; extra == 'test'
Requires-Dist: pytest>=6.0.0; extra == 'test'
